[
  {
    "id": "md-9bae96b1",
    "title": "Action Kamen",
    "author": "Nishiwaki Datto",
    "genres": [
      "Sci-Fi",
      "Action",
      "Mecha",
      "Superhero"
    ],
    "status": "completed",
    "total_chapters": 22,
    "description": "In order to return people that have turned into monsters from the seed of hatred, our hero in mask have sealed his fist… Action mask who also appears in Japan’s national comedy manga \"Crayon Shin-...",
    "cover_url": "https://uploads.mangadex.org/covers/9bae96b1-abb4-4da0-b0c1-ab7cff33c316/"
  },
  {
    "id": "md-8f883600",
    "title": "Violence Action",
    "author": "Sawada Shin",
    "genres": [
      "Action",
      "Comedy",
      "Drama"
    ],
    "status": "ongoing",
    "total_chapters": 0,
    "description": "Kikuno Kei, nickname \"Kay\", is a normal university student, and a part time hitwoman.",
    "cover_url": "https://uploads.mangadex.org/covers/8f883600-9655-4498-b87c-65328cada285/"
  },
  {
    "id": "md-69de2274",
    "title": "Tokusou Sentai Dekaranger the Movie: Full Blast Action",
    "author": "Takeyama Yuusuke",
    "genres": [
      "Sci-Fi",
      "Action",
      "Mecha"
    ],
    "status": "completed",
    "total_chapters": 4,
    "description": "A criminal gang called the Gas Drinkers have transformed Planet Lesley into a dead world. To fight them, the Leslian Dekaranger Mary lends her assistance to Earth's Special Police, the six Dekarangers...",
    "cover_url": "https://uploads.mangadex.org/covers/69de2274-e7bc-4f0c-946e-54013dbad42e/"
  },
  {
    "id": "md-f3bdf2b4",
    "title": "Action Idols - Age of Young Dragons",
    "author": "김태관",
    "genres": [
      "Action",
      "Comedy",
      "Drama"
    ],
    "status": "cancelled",
    "total_chapters": 25,
    "description": "After the suspicious death of her brother, Zena Han decides to continue her training to become a top martial arts student so that she can be accepted into a clan and obtain the coveted title of action...",
    "cover_url": "https://uploads.mangadex.org/covers/f3bdf2b4-ddb0-4917-8a67-10034e321c9b/"
  },
  {
    "id": "md-3bd54dc7",
    "title": "Action Rocky",
    "author": "Motoyuki Asai",
    "genres": [
      "Action"
    ],
    "status": "completed",
    "total_chapters": 58,
    "description": "Sequel to \" Famicom Rocky \". All the games that appear are original.",
    "cover_url": "https://uploads.mangadex.org/covers/3bd54dc7-2480-40ad-8f85-f6292bfca83c/"
  },
  {
    "id": "md-07661b20",
    "title": "Executive Action",
    "author": "Tsuchiyama Shigeru",
    "genres": [
      "Thriller"
    ],
    "status": "completed",
    "total_chapters": 0,
    "description": "A part of the Gekiga Roadshow",
    "cover_url": "https://uploads.mangadex.org/covers/07661b20-1601-4b98-be6c-258c9d95828e/"
  },
  {
    "id": "md-f1e87351",
    "title": "A Great Action Drama! Beware Kisara, Yogekidan on the Wind!!",
    "author": "Inoue Sora",
    "genres": [
      "Action"
    ],
    "status": "completed",
    "total_chapters": 0,
    "description": "",
    "cover_url": "https://uploads.mangadex.org/covers/f1e87351-b621-4044-a4df-40ee1f268e0e/"
  },
  {
    "id": "md-040003e5",
    "title": "Action Heroine Cheer Fruits",
    "author": "Azuse",
    "genres": [
      "Comedy",
      "Superhero",
      "Magical Girls",
      "Fantasy",
      "Slice of Life"
    ],
    "status": "completed",
    "total_chapters": 6,
    "description": "The \"local heroine fighter\" of a certain city became popular and a national star. Because of this, \"local heroines\" debuted in various other places, and their action live events became a hit trend nat...",
    "cover_url": "https://uploads.mangadex.org/covers/040003e5-afe0-42fa-85c0-1c965ef093cd/"
  },
  {
    "id": "md-ae766811",
    "title": "Bloomed In Action",
    "author": "Shiono Etorouji",
    "genres": [
      "Action",
      "Comedy"
    ],
    "status": "completed",
    "total_chapters": 7,
    "description": "When an enemy explosion leaves private military soldier Terawaki Ryo nearly dead, a secret organization rebuilds his body using the research they have done in human revivals. Unfortunately for him, th...",
    "cover_url": "https://uploads.mangadex.org/covers/ae766811-f461-4000-ade9-6ebc273eab5b/"
  },
  {
    "id": "md-6754e28a",
    "title": "Action Star",
    "author": "Miki Kousuke",
    "genres": [
      "Action"
    ],
    "status": "completed",
    "total_chapters": 8,
    "description": "Domon Hayato, a Japanese high school student who aims to become a big star in the Hong Kong action world, is a true kung fu otaku who even skips school tests to practice fighting action. When he learn...",
    "cover_url": "https://uploads.mangadex.org/covers/6754e28a-9017-4184-b4eb-916837171215/"
  },
  {
    "id": "md-6df12228",
    "title": "Himitsu.",
    "author": "Ootomo Megane",
    "genres": [
      "Girls' Love",
      "Slice of Life"
    ],
    "status": "completed",
    "total_chapters": 6,
    "description": "- A Passing Story  \nA school doctor recounts a romance from her own school days.  \n  \n- Pink  \nA love triangle. It's set in the same school as \"A Passing Story.\"  \n  \n- Romance  \nA couple from the sam...",
    "cover_url": "https://uploads.mangadex.org/covers/6df12228-0fe9-438a-897d-263611eb0265/"
  },
  {
    "id": "md-3a478b1b",
    "title": "Romance De Wa Nai Ni Shiro",
    "author": "Fumi Kyouko",
    "genres": [
      "Romance",
      "Drama"
    ],
    "status": "completed",
    "total_chapters": 0,
    "description": "",
    "cover_url": "https://uploads.mangadex.org/covers/3a478b1b-0f07-491b-9157-c8eb59603e7a/"
  },
  {
    "id": "md-215cc0e1",
    "title": "Romance is the Sparkle of the Sword 2 Plus",
    "author": "Mario Kaneda",
    "genres": [
      "Action"
    ],
    "status": "completed",
    "total_chapters": 0,
    "description": "PS version heroine Alicia also appears!\n\nCapture the silver rainbow and her heart with sword and magic! A comic version of the popular romance RPG that also includes the Shonen Ace feature featuring A...",
    "cover_url": "https://uploads.mangadex.org/covers/215cc0e1-17c6-4d56-ac4e-d190af3e70cc/"
  },
  {
    "id": "md-25c8ae81",
    "title": "Memoirs of Romance",
    "author": "Mangjae",
    "genres": [
      "Romance",
      "Boys' Love",
      "Drama"
    ],
    "status": "completed",
    "total_chapters": 0,
    "description": "There are 5 famous pretty boys at school. Their odd natures disagree with their good looks. Now that Jun-Oh is their target, what will happen?",
    "cover_url": "https://uploads.mangadex.org/covers/25c8ae81-c071-42bb-989a-23eef9a0d85d/"
  },
  {
    "id": "md-03b93305",
    "title": "Drawing Romance (Pre-Serialization)",
    "author": "Chocochip (말초코칩)",
    "genres": [
      "Romance",
      "Comedy",
      "Drama"
    ],
    "status": "completed",
    "total_chapters": 0,
    "description": "**Note:**\n- Before getting serialized on the Toptoon platform on May 20, 2019, It was published on DC Inside in short form. (Source : Namu Wiki, translated)",
    "cover_url": "https://uploads.mangadex.org/covers/03b93305-78be-4716-a111-5218c46523f9/"
  },
  {
    "id": "md-680ecffc",
    "title": "Horror Romance: Cheoyong",
    "author": "Lee Yoon-Mi",
    "genres": [
      "Romance",
      "Comedy",
      "Mystery"
    ],
    "status": "completed",
    "total_chapters": 44,
    "description": "\"Lee Yeojin,\" the heroine of Cheoyoung's urban legend, is suffering from a strange somnambulism.   \n  \nA special man appears in front of her, who was dreaming of a fierce, passionate love.  \n  \n\"Won J...",
    "cover_url": "https://uploads.mangadex.org/covers/680ecffc-279a-4ce4-a6b7-eae91c51d265/"
  },
  {
    "id": "md-68fa827f",
    "title": "Betrayalism Romance",
    "author": "Southern Fruit Tea",
    "genres": [
      "Romance",
      "Drama"
    ],
    "status": "completed",
    "total_chapters": 0,
    "description": "Bae Shinju, Jang Maro, Yoo Hana, and Cho Jihoon were close friends since elementary school. During their 2nd year of High School, Maro chooses to confess to Shinju. Shinju's refusal to respond to Maro...",
    "cover_url": "https://uploads.mangadex.org/covers/68fa827f-499a-46f8-b392-a872a2dd748a/"
  },
  {
    "id": "md-41506c14",
    "title": "Youth Romance",
    "author": "Miwool (미울)",
    "genres": [
      "Romance",
      "Drama",
      "Slice of Life"
    ],
    "status": "completed",
    "total_chapters": 108,
    "description": "",
    "cover_url": "https://uploads.mangadex.org/covers/41506c14-e8bb-4971-b5fd-48437d6090c5/"
  },
  {
    "id": "md-48182d54",
    "title": "Romance no Tamago",
    "author": "Umino Tsunami",
    "genres": [
      "Romance",
      "Comedy",
      "Slice of Life"
    ],
    "status": "completed",
    "total_chapters": 0,
    "description": "Includes two other works: \"Super Girl\" and \"Watashi wa Flamingo ni Naritai\".",
    "cover_url": "https://uploads.mangadex.org/covers/48182d54-aa49-46e0-a9c9-0e8c38e3e8b4/"
  },
  {
    "id": "md-5058228d",
    "title": "Midnight Cinderella Ikemen Royal Romance ~ The Royal Knight ~",
    "author": "Machida Ritsu",
    "genres": [
      "Historical",
      "Romance",
      "Fantasy"
    ],
    "status": "completed",
    "total_chapters": 30,
    "description": "“You are now the princess elect of this kingdom.” You were just a commoner visiting the palace. But in a twist of fate, you were selected as the kingdom's princess! What awaited you was an encount...",
    "cover_url": "https://uploads.mangadex.org/covers/5058228d-e5ae-4f5f-b1e9-df8928eb8f7e/"
  },
  {
    "id": "md-895e21a6",
    "title": "Siwoldeu Fantasy",
    "author": "진돌 / 히디",
    "genres": [
      "Fantasy"
    ],
    "status": "ongoing",
    "total_chapters": 0,
    "description": "Jorace, the warrior on the road to success. \nMarriage with an unidentified, super-cool handsome man has come.\nBy the way... the mother-in-law is a big. ㄴ(°0°)ㄱ",
    "cover_url": "https://uploads.mangadex.org/covers/895e21a6-62f8-4bdc-975d-d81aa63e4446/"
  },
  {
    "id": "md-b6277ef2",
    "title": "Transmigrating to the Romantic Fantasy Novel Written by My Daughter",
    "author": "Hyeyong (혜용)",
    "genres": [
      "Romance",
      "Drama",
      "Fantasy"
    ],
    "status": "ongoing",
    "total_chapters": 0,
    "description": "Park Soonja stumbles on a mountain and passes out, waking up as the heroine of her daughter's romance-fantasy novel, Belita Partel. She first enjoys her new life and youth, until it hits her that her ...",
    "cover_url": "https://uploads.mangadex.org/covers/b6277ef2-12cd-4b89-a747-bea0fdd9e014/"
  },
  {
    "id": "md-80c899e9",
    "title": "Yankee to Fantasy",
    "author": "Futaba You",
    "genres": [
      "Action"
    ],
    "status": "ongoing",
    "total_chapters": 0,
    "description": "",
    "cover_url": "https://uploads.mangadex.org/covers/80c899e9-e140-431e-ae54-f97d6ece12eb/"
  },
  {
    "id": "md-e8b55624",
    "title": "Fantasy ni wa Najimenai: Arafoo Otoko, Hard Mode Isekai ni Ten'i Shita kedo Kekkyoku Musou",
    "author": "Senmu",
    "genres": [
      "Action",
      "Romance",
      "Isekai",
      "Fantasy"
    ],
    "status": "completed",
    "total_chapters": 18,
    "description": "",
    "cover_url": "https://uploads.mangadex.org/covers/e8b55624-0181-48b9-8c6e-ec420fb9fc16/"
  },
  {
    "id": "md-81e138cb",
    "title": "Final Fantasy VII - Nagisa no Yakusoku (Doujinshi)",
    "author": "Honya Ranko",
    "genres": [
      "Comedy"
    ],
    "status": "completed",
    "total_chapters": 0,
    "description": "Tifa and Aerith take a detour to Costa del Sol with Cloud, where the two friends swear an oath to one another. (slight AerithxTifa pairing)",
    "cover_url": "https://uploads.mangadex.org/covers/81e138cb-ec0f-47a8-833f-854e1e3104ec/"
  },
  {
    "id": "md-1ec59012",
    "title": "Final Fantasy XII - Day Tripper (Doujinshi)",
    "author": "Azuki-2Goh",
    "genres": [
      "Boys' Love",
      "Adventure"
    ],
    "status": "completed",
    "total_chapters": 0,
    "description": "Basch is wounded hunting a mark, leaving Balthier alone in the wilds, with monsters bearing down.",
    "cover_url": "https://uploads.mangadex.org/covers/1ec59012-1ef1-4235-b08e-5251a7ca8f97/"
  },
  {
    "id": "md-7b0f57b3",
    "title": "Touhou - Ku-sou Mangekyou: Fantasy Kaleidoscope (Doujinshi)",
    "author": "Hirasaka Makoto",
    "genres": [
      "Fantasy"
    ],
    "status": "completed",
    "total_chapters": 0,
    "description": "",
    "cover_url": "https://uploads.mangadex.org/covers/7b0f57b3-b551-4bb2-8fa4-b9dfd34634ed/"
  },
  {
    "id": "md-8be7b061",
    "title": "Final Fantasy XII - Creep Show (Doujinshi)",
    "author": "Cinnamon (Circle)",
    "genres": [
      "Romance",
      "Boys' Love",
      "Drama"
    ],
    "status": "completed",
    "total_chapters": 0,
    "description": "Balthier/Basch  \n  \nTakes place between 'Beyond the Sky' and 'Your Voice Calling'. Balthier tries to figure out where he stands in his relationship with Basch.",
    "cover_url": "https://uploads.mangadex.org/covers/8be7b061-5a93-40cb-9816-f63be7dca650/"
  },
  {
    "id": "md-28f28642",
    "title": "Id: The Greatest Fusion Fantasy",
    "author": "Kenny A.T.",
    "genres": [
      "Action",
      "Romance",
      "Comedy",
      "Adventure",
      "Isekai",
      "Fantasy"
    ],
    "status": "cancelled",
    "total_chapters": 178,
    "description": "We find Chunwha in a world beyond his own… There he will struggle to find his own purpose among the many inhabitants of the new world including elves, dwarves, and even mages! As we watch him grow i...",
    "cover_url": "https://uploads.mangadex.org/covers/28f28642-4bbd-48f3-9f66-30adc7cdf992/"
  },
  {
    "id": "md-81fed896",
    "title": "Lord Baby Runs a Romance Fantasy With Cash (Promo)",
    "author": "Ju Hyeon",
    "genres": [
      "Romance",
      "Comedy",
      "Isekai",
      "Drama",
      "Fantasy"
    ],
    "status": "completed",
    "total_chapters": 0,
    "description": "***This is a promotional oneshot for a novel of the same name.***\n\n---\nI lived suffering without a home, religion, or parents, but an angel appeared and reincarnated me.\n\n\"You, a pro when it comes to ...",
    "cover_url": "https://uploads.mangadex.org/covers/81fed896-7455-48bc-bb43-13c28d733218/"
  },
  {
    "id": "md-6dd8d9b7",
    "title": "Tokyo Name Tank - Horror Selection",
    "author": "Kouno Tomoyuki",
    "genres": [
      "Horror"
    ],
    "status": "completed",
    "total_chapters": 5,
    "description": "Horror anthology.\n\nChapters:\n1. ***Ushibonke*** (うしぼとけ) by Hairon\n2. ***Soujiya no Kiyoko-san*** (掃除屋の清子さん) by Ayame Gonta\n3. ***Akujiki no Taiji*** (悪食の鯛次) by Kage...",
    "cover_url": "https://uploads.mangadex.org/covers/6dd8d9b7-285e-4714-b93a-02486cf70026/"
  },
  {
    "id": "md-962e1609",
    "title": "Kanako Inuki's Horror Theater: Sacrifice",
    "author": "Inuki Kanako",
    "genres": [
      "Horror",
      "Mystery"
    ],
    "status": "completed",
    "total_chapters": 9,
    "description": "Various strange phenomena occur at school! Do ghosts really exist? My classmates are ignoring me and enjoying the school's ghost stories. There's a story about a girl who fell into a toilet, a story a...",
    "cover_url": "https://uploads.mangadex.org/covers/962e1609-1eb0-41a5-8f29-1ed880e3dc59/"
  },
  {
    "id": "md-928d50fc",
    "title": "Horror Newspaper II",
    "author": "Tsunoda Jirou",
    "genres": [
      "Thriller",
      "Action",
      "Psychological",
      "Adventure",
      "Philosophical",
      "Drama",
      "Horror",
      "Slice of Life",
      "Mystery",
      "Tragedy"
    ],
    "status": "completed",
    "total_chapters": 38,
    "description": "(from ebookjapan):\n\nYuko Hondo is an ordinary girl who becomes possessed by the \"Horror Newspaper\" and is plunged into the depths of misfortune and fear. The newspaper causes a chain of turmoil around...",
    "cover_url": "https://uploads.mangadex.org/covers/928d50fc-3c0b-47c0-b423-e5e52e08466f/"
  },
  {
    "id": "md-cfcc6eef",
    "title": "Truly Scary Horror Story",
    "author": "Naphthalin Mizushima",
    "genres": [
      "Romance",
      "Horror"
    ],
    "status": "ongoing",
    "total_chapters": 0,
    "description": "",
    "cover_url": "https://uploads.mangadex.org/covers/cfcc6eef-60e2-4a82-bd7f-27cfd08b7f52/"
  },
  {
    "id": "md-fe89bc3d",
    "title": "Inuki Kanako’s Horror Theater: Ubasute",
    "author": "Inuki Kanako",
    "genres": [
      "Horror",
      "Fantasy",
      "Mystery"
    ],
    "status": "completed",
    "total_chapters": 2,
    "description": "*Ubasute means ''Abandoning an Old Woman''\n\nOne day a vending machine was suddenly installed in front of a small store in a small town. When I asked the old lady that owns the store, she told me that ...",
    "cover_url": "https://uploads.mangadex.org/covers/fe89bc3d-24fb-41f8-b684-a896463984b4/"
  },
  {
    "id": "md-21cc5ff9",
    "title": "Fatal Fury: Devil Street of Horror",
    "author": "Ishikawa Ken",
    "genres": [
      "Action",
      "Comedy",
      "Sports",
      "Adventure",
      "Drama"
    ],
    "status": "completed",
    "total_chapters": 10,
    "description": "Hearing news of demons plaguing the Hakkyokuseiken dojo, Andy leaves his friends to investigate it. To his shock, the rumors are true and the demons' overlord is the formerly deceased Geese. Using his...",
    "cover_url": "https://uploads.mangadex.org/covers/21cc5ff9-1094-4639-a15d-665e9caad2dd/"
  },
  {
    "id": "md-3431de09",
    "title": "Go Nagai Horror Story Collection: Skull Manor",
    "author": "Nagai Go",
    "genres": [
      "Drama",
      "Horror"
    ],
    "status": "completed",
    "total_chapters": 5,
    "description": "A collection of short horror stories.  \n  \nThe volume contains:  \n* RED STRING (Shueisha) 1990  \n* Oni Gokko (Chuokoronsha) 1993  \n* Oni Kon Shiki (Chuokoronsha) 1993  \n* Ihin (Josei Sebun) 1977  \n* D...",
    "cover_url": "https://uploads.mangadex.org/covers/3431de09-2e74-473a-b6b4-8802350b455f/"
  },
  {
    "id": "md-b0f51e1b",
    "title": "House of the Horror",
    "author": "MEIMU",
    "genres": [
      "Thriller",
      "Psychological",
      "Horror",
      "Mystery",
      "Tragedy"
    ],
    "status": "completed",
    "total_chapters": 6,
    "description": "Six horror, dark, and gruesome stories authored by Meimu.\n\n1. House Of The Horror\n2. At The Confines Of The Mother Earth\n3. Doll\n4. The Monstrous Laboratory\n5. Sirens - Form Of Aquatic Life\n6. Bloodre...",
    "cover_url": "https://uploads.mangadex.org/covers/b0f51e1b-b564-4d56-916f-ce6b4b6aa483/"
  },
  {
    "id": "md-81c5f816",
    "title": "Horror Anthology Comic: Blindside",
    "author": "Inuki Kanako",
    "genres": [
      "Psychological",
      "Romance",
      "Comedy",
      "Drama",
      "Horror",
      "Tragedy"
    ],
    "status": "completed",
    "total_chapters": 9,
    "description": "An anthology of horror one-shots by various artists.\n1. Shirayuki-hime (白雪姫, Snow White) [Ito Junji]; Manga Grimm Douwa 2014-12\n2. Prologue de Owaru Monogatari (プロローグで終わる物語...",
    "cover_url": "https://uploads.mangadex.org/covers/81c5f816-e03a-45a4-b0ae-127b2b757f0d/"
  },
  {
    "id": "md-3f7b7736",
    "title": "Junji Ito Horror Manga Collection",
    "author": "Ito Junji",
    "genres": [
      "Historical",
      "Psychological",
      "Comedy",
      "Drama",
      "Horror",
      "Slice of Life",
      "Mystery",
      "Tragedy"
    ],
    "status": "completed",
    "total_chapters": 3,
    "description": "**Note:** This is the first Complete Works set for Ito's works released in the late 90s. A new Complete Works set, titled the \"Junji Ito Masterpiece Selection\" is the one currently in print and the ed...",
    "cover_url": "https://uploads.mangadex.org/covers/3f7b7736-84c5-4f38-bf73-7266021f355a/"
  },
  {
    "id": "md-37789719",
    "title": "Kayoko Lullaby ~Seinen Manga Comedy~",
    "author": "Sasou Nami",
    "genres": [
      "Romance",
      "Comedy",
      "Drama",
      "Slice of Life"
    ],
    "status": "completed",
    "total_chapters": 11,
    "description": "(from ebookjapan):\nShojo mangaka Nami Saso's only (!?) seinen manga is a comedy manga! This work was serialized in Monthly Play Comic, and exploded in popularity! In fact, Akita Shoten was approached ...",
    "cover_url": "https://uploads.mangadex.org/covers/37789719-9efe-42ba-ba3a-1cc6da64e947/"
  },
  {
    "id": "md-927d687f",
    "title": "Inkya Danshi ga Keiken Shita, Urayamakeshikaran na Love Comedy",
    "author": "Homenoba",
    "genres": [
      "Romance",
      "Comedy",
      "Slice of Life"
    ],
    "status": "ongoing",
    "total_chapters": 0,
    "description": "",
    "cover_url": "https://uploads.mangadex.org/covers/927d687f-ceb6-4e56-baff-461d6660443a/"
  },
  {
    "id": "md-4ba616e9",
    "title": "Ore no Nounai Sentakushi ga, Gakuen Love-Comedy wo Zenryoku de Jama Shiteiru",
    "author": "Kasukabe Takeru",
    "genres": [
      "Romance",
      "Comedy",
      "Drama"
    ],
    "status": "completed",
    "total_chapters": 23,
    "description": "The story centers around Kanade Amakusa, a boy cursed with the mental power of \"absolute multiple-choice\"—a multiple-choice quiz will suddenly appear in his mind, and the choice he makes will become...",
    "cover_url": "https://uploads.mangadex.org/covers/4ba616e9-67d2-4276-92db-5d2922c65677/"
  },
  {
    "id": "md-591b6e03",
    "title": "Tsuyokute New Game na Love Comedy",
    "author": "Yano Keito",
    "genres": [
      "Romance",
      "Comedy"
    ],
    "status": "ongoing",
    "total_chapters": 0,
    "description": "Komine is an ordinary grade-school kid who is at the top of his class. And for good reason - after dying, this is actually his second run at life. Knowing everything from upcoming class subjects to fu...",
    "cover_url": "https://uploads.mangadex.org/covers/591b6e03-c02b-4362-aa75-b9066e21f46e/"
  },
  {
    "id": "md-4cb7265f",
    "title": "Ore no Nounai Sentakushi ga, Gakuen Love-Comedy o Zenryoku de Jama Shiteiru H",
    "author": "Kasukabe Takeru",
    "genres": [
      "Comedy"
    ],
    "status": "completed",
    "total_chapters": 9,
    "description": "Kanade Amakusa is a high-school student who is suffering from a curse called \"Absolute Choices\" (絶対選択肢, Zettai Sentakushi). This curse requires him to select an action from a list of two or ...",
    "cover_url": "https://uploads.mangadex.org/covers/4cb7265f-9183-429d-9c9f-0187827642e1/"
  },
  {
    "id": "md-6274fcab",
    "title": "Boku no Kokoro no Yabai Yatsu: Love Comedy ga Hajimaranai",
    "author": "Nanasaka Haika",
    "genres": [
      "Romance",
      "Comedy",
      "Slice of Life"
    ],
    "status": "ongoing",
    "total_chapters": 0,
    "description": "This time around, we follow Kana Ichikawa, Kyotaro’s big sis! She’s got a ton of gal pals, but she’s never had a guy friend before, let alone a boyfriend. She’s given up on ever being popular ...",
    "cover_url": "https://uploads.mangadex.org/covers/6274fcab-df09-4ac5-b516-14152bd031c7/"
  },
  {
    "id": "md-047bd4fe",
    "title": "Kumokiri-san wa Love Comedy ga Shitai",
    "author": "Keijiro",
    "genres": [
      "Romance"
    ],
    "status": "completed",
    "total_chapters": 0,
    "description": "Kanzaki-kun is a high school student who loves rom-com manga. However, for a certain reason, he knows better than anyone else that rom-coms don't actually exist in reality. Appearing before him is Kum...",
    "cover_url": "https://uploads.mangadex.org/covers/047bd4fe-f976-451c-9992-ae99a48a8fcd/"
  },
  {
    "id": "md-19253e97",
    "title": "After-School Comedy Club",
    "author": "Takashima Hiromi",
    "genres": [
      "Comedy"
    ],
    "status": "completed",
    "total_chapters": 12,
    "description": "Natsumi Kitano, a high school boy who also moonlights as a postcard writer for radio shows, often gets his submissions aired and earns laughs. However, his high school life is otherwise unremarkable a...",
    "cover_url": "https://uploads.mangadex.org/covers/19253e97-754e-4a2f-9217-7752e25e18a3/"
  },
  {
    "id": "md-e6a2681d",
    "title": "MaMa: It's Real Time Home-Made Comedy",
    "author": "Hosono Fujihiko",
    "genres": [
      "Comedy",
      "Slice of Life"
    ],
    "status": "completed",
    "total_chapters": 107,
    "description": "Koo Hagiwara, a high school dropout and aspiring chef, is determined to carry not only herself but also Misa, who has a child. Invincible youth, let's go boy, morning of independence! The long-awaited...",
    "cover_url": "https://uploads.mangadex.org/covers/e6a2681d-cc72-47df-986c-113b39f680dc/"
  },
  {
    "id": "md-9964801b",
    "title": "Love Comedy Encyclopedia",
    "author": "Tsukushiro Yuuri",
    "genres": [
      "Romance",
      "Comedy",
      "Slice of Life"
    ],
    "status": "completed",
    "total_chapters": 0,
    "description": "A collection of romcom shorts that are sometimes posted on the artist's twitter.",
    "cover_url": "https://uploads.mangadex.org/covers/9964801b-2053-43e4-90b7-029bd349b665/"
  },
  {
    "id": "md-59f4f28d",
    "title": "Sci-Fi Motion!",
    "author": "Nagano Noriko",
    "genres": [
      "Sci-Fi"
    ],
    "status": "completed",
    "total_chapters": 12,
    "description": "With a high-tension moe feel ♡ Noriko Nagano's retro SF romantic comedy GAG masterpiece collection is now available ☆ The title work is filled with the loveliness of the heroine Chiyomi, and the a...",
    "cover_url": "https://uploads.mangadex.org/covers/59f4f28d-da4f-4dd6-ad1a-4e2dc7cbd00d/"
  },
  {
    "id": "md-c88caaef",
    "title": "Sci-Fi Robot Classic: Transformers",
    "author": "Miyazoe Ikuo",
    "genres": [
      "Mecha"
    ],
    "status": "cancelled",
    "total_chapters": 0,
    "description": "",
    "cover_url": "https://uploads.mangadex.org/covers/c88caaef-0b6a-472a-8a37-144d615dac4d/"
  },
  {
    "id": "md-6a08b268",
    "title": "TEKNO: Sci-Fi Shonen Manga!",
    "author": "Blu Manga",
    "genres": [
      "Sci-Fi",
      "Action",
      "Psychological",
      "Comedy",
      "Mecha",
      "Philosophical"
    ],
    "status": "ongoing",
    "total_chapters": 0,
    "description": "IN FUTURA, the land of Techs... Tek is the only one who can't use them! But he will fight many battles to make it a better place to live! (Note: It gets good 200 chapters in.)\nSupport TEKNO here: http...",
    "cover_url": "https://uploads.mangadex.org/covers/6a08b268-e032-4198-a53a-ef705e592dc3/"
  },
  {
    "id": "md-d94106f9",
    "title": "Sf Kiseki",
    "author": "Caio Catarino",
    "genres": [
      "Action"
    ],
    "status": "ongoing",
    "total_chapters": 0,
    "description": "Namiki Denji has a problem - he fell in love with two girls at the same time, and can't tell who his true love really is.  \nThings just get worse when his grandaughter comes back from the future wishi...",
    "cover_url": "https://uploads.mangadex.org/covers/d94106f9-6062-4ba8-a3ad-77f460f060f2/"
  },
  {
    "id": "md-b4d8aed1",
    "title": "Spaceketeers",
    "author": "Matsumoto Leiji",
    "genres": [
      "Sci-Fi"
    ],
    "status": "completed",
    "total_chapters": 0,
    "description": "",
    "cover_url": "https://uploads.mangadex.org/covers/b4d8aed1-28d6-4eab-ae7e-2105771f48aa/"
  },
  {
    "id": "md-c61f3276",
    "title": "Takao Saito historical drama selection ~ Killer Whale",
    "author": "Saito Takao",
    "genres": [
      "Action"
    ],
    "status": "completed",
    "total_chapters": 3,
    "description": "",
    "cover_url": "https://uploads.mangadex.org/covers/c61f3276-9457-4505-9b3b-45151317ba89/"
  },
  {
    "id": "md-f2c96b35",
    "title": "Joya Kagemaru's Historical Drama Masterpiece Selection",
    "author": "Kagemaru Joya",
    "genres": [
      "Historical"
    ],
    "status": "completed",
    "total_chapters": 5,
    "description": "The world is the Sengoku period---\nWild samurai, blacksmiths, strategists, hunters, and young swordsmen who survive the turbulent times\nA collection of masterpieces by masters depicting their respecti...",
    "cover_url": "https://uploads.mangadex.org/covers/f2c96b35-e26e-4045-8ae7-c6027e3a9c42/"
  },
  {
    "id": "md-7b3ce718",
    "title": "A Selection of Historical Masterpieces",
    "author": "Yokoyama Mitsuteru",
    "genres": [
      "Historical"
    ],
    "status": "completed",
    "total_chapters": 25,
    "description": "a collection of short and medium-length historical manga!",
    "cover_url": "https://uploads.mangadex.org/covers/7b3ce718-266e-4e3b-b414-05d070d5acc1/"
  },
  {
    "id": "md-a88af475",
    "title": "Kareinaru Ai no Rekishi Emaki",
    "author": "Nagaoka Yoshiko",
    "genres": [
      "Historical"
    ],
    "status": "completed",
    "total_chapters": 0,
    "description": "",
    "cover_url": "https://uploads.mangadex.org/covers/a88af475-5aa4-4fb7-8256-c8ae65123c55/"
  },
  {
    "id": "md-59c62ee7",
    "title": "A Small Imaginative League of Legends Slice of Life",
    "author": "The shortlegged must sleep early",
    "genres": [
      "Comedy",
      "Slice of Life"
    ],
    "status": "ongoing",
    "total_chapters": 0,
    "description": "Cute LOL fanfic chapters that can be read in any order.",
    "cover_url": "https://uploads.mangadex.org/covers/59c62ee7-268f-43f6-a1fa-12d44cf14451/"
  },
  {
    "id": "md-3b0501d7",
    "title": "A Slice of My Life",
    "author": "Tan Jiu (坛九)",
    "genres": [
      "Adventure",
      "Philosophical",
      "Fantasy",
      "Slice of Life"
    ],
    "status": "completed",
    "total_chapters": 1,
    "description": "A young girl embarks on an adventure by walking on the path she liked. But things didn't turn out as good as she expected. However, she is saved by two people who become her most loving companions in ...",
    "cover_url": "https://uploads.mangadex.org/covers/3b0501d7-716e-43c2-b73b-c128995b899e/"
  },
  {
    "id": "md-8c16a26a",
    "title": "Incidents in the Life of a Slave Girl",
    "author": "Harriet Ann Jacobs",
    "genres": [
      "Historical",
      "Drama",
      "Tragedy"
    ],
    "status": "ongoing",
    "total_chapters": 0,
    "description": "",
    "cover_url": "https://uploads.mangadex.org/covers/8c16a26a-c4b3-4694-8ccb-52ea8a943cdb/"
  },
  {
    "id": "md-359fab8d",
    "title": "MaOL! ~Shachiku OL to Isekai Saikyou Maou Irekawari Seikatsu~",
    "author": "Yamigishiki Cult",
    "genres": [
      "Comedy",
      "Isekai",
      "Fantasy"
    ],
    "status": "completed",
    "total_chapters": 37,
    "description": "Mao, a timid OL, gets crashed into by a bicycle and switches bodies with a demon king from another world.",
    "cover_url": "https://uploads.mangadex.org/covers/359fab8d-25e8-420b-858a-665881312129/"
  },
  {
    "id": "md-e3ccc778",
    "title": "Shachiku, Dungeon Darake no Sekai de Koyuu Skill \"Gouyoku\" wo Te ni Irete Saikyou no Balance Breaker ni Naru",
    "author": "Jin Aino",
    "genres": [
      "Action",
      "Fantasy"
    ],
    "status": "completed",
    "total_chapters": 27,
    "description": "In present-day Japan, countless dungeons appeared. Hekoobi Keita, a corporate slave exploited by a black company, goes into Shibuya's dungeon indifferently. but thanks to a rare monster he (coincident...",
    "cover_url": "https://uploads.mangadex.org/covers/e3ccc778-18f7-4682-9b2c-707e3fbf3767/"
  },
  {
    "id": "md-003233a9",
    "title": "Arasaa Majutsushi no Yuru ii Harem Life ~Black Shachiku ga Isekai de Jiyuu Kimama ni Yuukyuu Shouka~",
    "author": "しんこせい",
    "genres": [
      "Romance",
      "Adventure",
      "Isekai"
    ],
    "status": "ongoing",
    "total_chapters": 0,
    "description": "This is the story of a nearly-30-year-old office worker who suddenly remembers—he was a powerful mage in a past life! Now, he switches back and forth between the two worlds, living a laid-back, slow...",
    "cover_url": "https://uploads.mangadex.org/covers/003233a9-5e9c-47ff-8e07-e7670c7ea48d/"
  },
  {
    "id": "md-97223152",
    "title": "BOX! Kira Ito Tanpenshuu",
    "author": "Kira Ito (吉良いと)",
    "genres": [
      "Romance",
      "Comedy",
      "Slice of Life",
      "Tragedy"
    ],
    "status": "ongoing",
    "total_chapters": 0,
    "description": "A work packed with stories that make you cry, smile, and heal. A compilation of original short stories, including commercial oneshots and manga previously published on Twitter or Pixiv.\n\nList of Stori...",
    "cover_url": "https://uploads.mangadex.org/covers/97223152-aefd-4f9b-91c9-39393d8494a0/"
  },
  {
    "id": "md-055dc933",
    "title": "Mystery",
    "author": "Banji",
    "genres": [
      "Drama",
      "Fantasy"
    ],
    "status": "ongoing",
    "total_chapters": 0,
    "description": "'Mystery' is what Garam thinks of the creature he accidentally awakened from a deep, long sleep. Her beauty is bewitching and it catches his attention ever since their first meeting. Enthralled by her...",
    "cover_url": "https://uploads.mangadex.org/covers/055dc933-3579-4650-9e2e-a64d077865e7/"
  },
  {
    "id": "md-7a501961",
    "title": "Pastoral Bible",
    "author": "Jin Qiu",
    "genres": [
      "Romance",
      "Comedy",
      "Adventure",
      "Drama",
      "Mystery"
    ],
    "status": "completed",
    "total_chapters": 21,
    "description": "A being from another dimension was summoned to the human world by a rebellious high school student. She reminisces about her hometown while he just wants to go home. Living together they start to beco...",
    "cover_url": "https://uploads.mangadex.org/covers/7a501961-6560-451c-b546-2de2cb6cf335/"
  },
  {
    "id": "md-31acae21",
    "title": "Layton Mystery Detective Agency: Katri's Puzzle Solving Files",
    "author": "Orito Kahori",
    "genres": [
      "Comedy"
    ],
    "status": "completed",
    "total_chapters": 10,
    "description": "\"-Reality is always rare!\" ``Layton Mystery Detective Agency'' was opened by Catrie, a girl who loves mysterious riddles as much as she loves fashion and sweets. Difficult cases that occur in London a...",
    "cover_url": "https://uploads.mangadex.org/covers/31acae21-e957-4f79-8bbd-42b5e6302365/"
  },
  {
    "id": "md-d65f3eef",
    "title": "Gogora Dodora - 4th Dimension Mystery",
    "author": "Hino Hideshi",
    "genres": [
      "Sci-Fi",
      "Horror",
      "Fantasy"
    ],
    "status": "completed",
    "total_chapters": 9,
    "description": "One night while star gazing neighbors Haruhiko and Fuko encounter strange lights in the sky...the next day they wake up to find themselves in an entirely new and strange world...",
    "cover_url": "https://uploads.mangadex.org/covers/d65f3eef-5be6-461f-9265-4199cc143d52/"
  },
  {
    "id": "md-0ca3d7eb",
    "title": "Comic M: Hayakawa Shobou Souritsu 70-shuunen Kinen Comic Anthology 〔Mystery Hen〕",
    "author": "Sakata Yasuko",
    "genres": [
      "Comedy",
      "Drama",
      "Fantasy",
      "Mystery"
    ],
    "status": "completed",
    "total_chapters": 19,
    "description": "Publisher Hayakawa is celebrating its 70th anniversary with two manga anthology reprints. One collection is dedicated to mystery works while the other compiles sci-fi stories printed over the publishe...",
    "cover_url": "https://uploads.mangadex.org/covers/0ca3d7eb-e6c8-4afb-b2ae-c73d4f5a517b/"
  },
  {
    "id": "md-7bfca64f",
    "title": "Shinai naru A-jou e no Mystery",
    "author": "Morie Satoshi",
    "genres": [
      "Psychological",
      "Romance",
      "Drama",
      "Mystery"
    ],
    "status": "completed",
    "total_chapters": 10,
    "description": "Ayano is a girl with her head in the clouds: she loves reading so much that she scarcely pays attention to the real world. Hoping to bring her back to reality, Ayano’s mother sends her to Noumi Taka...",
    "cover_url": "https://uploads.mangadex.org/covers/7bfca64f-3951-421a-8d95-ecda6fcdc418/"
  },
  {
    "id": "md-3438bf20",
    "title": "Logical Mystery Tour ~Science Sweets Arc~",
    "author": "Matsumoto Yuusuke",
    "genres": [
      "Adventure"
    ],
    "status": "ongoing",
    "total_chapters": 0,
    "description": "The friends go on another science adventure. This time, involving food! A story about how to master sweets-making using the power of science.",
    "cover_url": "https://uploads.mangadex.org/covers/3438bf20-9bbf-43b4-96b7-c28ec3ce605c/"
  },
  {
    "id": "md-061cfc5e",
    "title": "Asami Mitsuhiko Mystery File",
    "author": "Nakamura Sae",
    "genres": [
      "Mystery"
    ],
    "status": "completed",
    "total_chapters": 1,
    "description": "Popular actor “Takuo Eki” visited Karuizawa sensei. His mother is being threatened. Mitsuhiko heads to Kagoshima at the request of Sensei and \"Travel and History\" editor-in-chief Fujita! Where is ...",
    "cover_url": "https://uploads.mangadex.org/covers/061cfc5e-2fcb-49bf-bb9a-89ac801ec089/"
  },
  {
    "id": "md-8b412589",
    "title": "Layton Brothers Mystery Room: Perfect Crime Puzzle",
    "author": "Yaminabe Terumin",
    "genres": [
      "Mystery"
    ],
    "status": "ongoing",
    "total_chapters": 0,
    "description": "Level 5's hit Professor Layton series sees the smartphone title \"Layton Brothers Mystery Room\" make its manga debut! Starring none other than Professor Layton's son!? Watch as the strongest duo solve ...",
    "cover_url": "https://uploads.mangadex.org/covers/8b412589-cf83-4e8a-9013-a4a1ded5d864/"
  },
  {
    "id": "md-f2f92ac1",
    "title": "Mystery ga Saku",
    "author": "haruoka",
    "genres": [
      "Mystery"
    ],
    "status": "ongoing",
    "total_chapters": 0,
    "description": "",
    "cover_url": "https://uploads.mangadex.org/covers/f2f92ac1-adb4-4fb4-b673-c0d63332cec4/"
  },
  {
    "id": "md-fdf5b3a4",
    "title": "Legends of Masters: Sports Edition",
    "author": "Mutsu Toshiyuki",
    "genres": [
      "Sports"
    ],
    "status": "cancelled",
    "total_chapters": 3,
    "description": "[Yoshinori Sato]\nPitcher. Born on September 11, 1954. He is 181 cm tall and weighs 86 kg. He is a right-handed pitcher. He is from Hokkaido. Hakodate Yuto High School -- Nihon University -- Hankyu Ori...",
    "cover_url": "https://uploads.mangadex.org/covers/fdf5b3a4-871c-4e65-a84a-2005929af3ee/"
  },
  {
    "id": "md-ecbcd0a7",
    "title": "Does Love at First Sight Exist in E-Sports?",
    "author": "路嘻法",
    "genres": [
      "Romance",
      "Boys' Love",
      "Sports",
      "Drama"
    ],
    "status": "completed",
    "total_chapters": 90,
    "description": "Having nothing better to do, Asia’s champion decided to carry a girl in the game. With great difficulty, he finally convinced the girl he carried to turn on her mic, only to discover that the other ...",
    "cover_url": "https://uploads.mangadex.org/covers/ecbcd0a7-b06b-4370-ae3e-424fae40ebc8/"
  },
  {
    "id": "md-ac78abaa",
    "title": "Gothic Sports",
    "author": "Hage Anike",
    "genres": [
      "Romance",
      "Sports",
      "Drama"
    ],
    "status": "completed",
    "total_chapters": 0,
    "description": "Anya, the new girl at Lucrece High, just isn't fitting in. Her dream is to join one of the school's elite sports teams, but when she tries out, she's instantly rejected! Anya doesn't get mad, though\ufffd\ufffd...",
    "cover_url": "https://uploads.mangadex.org/covers/ac78abaa-a9ba-4db0-b09a-eb54d8708310/"
  },
  {
    "id": "md-7b74e19a",
    "title": "Sports Battle Royale",
    "author": "Aoyama Hiro",
    "genres": [
      "Sports"
    ],
    "status": "completed",
    "total_chapters": 0,
    "description": "",
    "cover_url": "https://uploads.mangadex.org/covers/7b74e19a-9d42-4857-a85e-cd8d3d2667f7/"
  },
  {
    "id": "md-c7835d6d",
    "title": "Lots of Sports",
    "author": "Aoyama Hiro",
    "genres": [
      "Sports"
    ],
    "status": "cancelled",
    "total_chapters": 0,
    "description": "",
    "cover_url": "https://uploads.mangadex.org/covers/c7835d6d-fc37-4a0d-956a-1ecd6c0f6ed1/"
  },
  {
    "id": "md-b708c549",
    "title": "Sportsman Sasuke",
    "author": "Terada Hiro",
    "genres": [
      "Sports"
    ],
    "status": "completed",
    "total_chapters": 0,
    "description": "What if ninjas met baseball!?\nThe exciting ninjutsu baseball manga by Tokiwaso's Terra is republished!\n*Special recording*\n“We were just students at a terakoya school!” Fujiko Fujio (A) 10,000-wor...",
    "cover_url": "https://uploads.mangadex.org/covers/b708c549-b288-495a-8166-6c4e358eb86b/"
  },
  {
    "id": "md-fc364783",
    "title": "Sportsman Kintaro: Academic Edition",
    "author": "Terada Hiro",
    "genres": [
      "Sports"
    ],
    "status": "completed",
    "total_chapters": 36,
    "description": "\"Sportsman Kintaro'' is a monumental baseball manga that was serialized in \"Weekly Shonen Sunday'' for five years starting with its first issue in 1959. Kintaro and Momotaro, celebrities from fairy ta...",
    "cover_url": "https://uploads.mangadex.org/covers/fc364783-9648-480d-9410-19f75893044d/"
  },
  {
    "id": "md-2b56406d",
    "title": "Saikyou no Onna Youhei - Kinmirai de Sports Bishoujo to Naru",
    "author": "Nokonoko Daioh",
    "genres": [
      "Action",
      "Sports"
    ],
    "status": "ongoing",
    "total_chapters": 0,
    "description": "",
    "cover_url": "https://uploads.mangadex.org/covers/2b56406d-42ba-448e-b1c3-cd3f081100b2/"
  },
  {
    "id": "md-6c899bc9",
    "title": "Blood Sports",
    "author": "Yoshida Akimi",
    "genres": [
      "Thriller",
      "Action",
      "Comedy",
      "Crime",
      "Drama"
    ],
    "status": "completed",
    "total_chapters": 0,
    "description": "",
    "cover_url": "https://uploads.mangadex.org/covers/6c899bc9-c11d-4793-8797-2c0335fa3b66/"
  },
  {
    "id": "md-5bac727d",
    "title": "FOG (E-Sports)",
    "author": "Manman He Qi Duo (漫漫何其多)",
    "genres": [
      "Romance",
      "Boys' Love",
      "Drama"
    ],
    "status": "completed",
    "total_chapters": 121,
    "description": "Two years ago, Yu Sui had his teammate sold out, and had himself criticized by the public. He didn't care about any of it. The only thing he cared about was the kid on his team, Shi Luo. After coming ...",
    "cover_url": "https://uploads.mangadex.org/covers/5bac727d-26fd-4428-b195-1852eb29ab66/"
  }
]